leonardo/Colour.py
leonardo/Gradient.py
leonardo/Scheme.py
leonardo/__init__.py
leonardo/colour_schemes.py
leonardo/colourize.py
leonardo/convert_rgb_to_hsl.py
leonardo/data_files/colour_schemes.pickle
leonardo/data_files/svg_colours.pickle
leonardo/data_files/x11_colours.pickle
leonardo-2019.12.30.1.dist-info/METADATA
leonardo-2019.12.30.1.dist-info/WHEEL
leonardo-2019.12.30.1.dist-info/top_level.txt
leonardo-2019.12.30.1.dist-info/zip-safe
leonardo-2019.12.30.1.dist-info/RECORD
