Metadata-Version: 2.1
Name: leonardo
Version: 2019.12.30.1
Summary: Python library working with colours
Home-page: https://github.com/idin/leonardo
Author: Idin
Author-email: py@idin.ca
License: MIT
Keywords: colour
Platform: UNKNOWN
Classifier: Development Status :: 3 - Alpha
Classifier: Intended Audience :: Developers
Classifier: License :: OSI Approved :: MIT License
Classifier: Programming Language :: Python :: 3 :: Only
Classifier: Programming Language :: Python :: 3.6
Classifier: Programming Language :: Python :: 3.7
Classifier: Topic :: Software Development :: Libraries :: Python Modules
Requires-Python: ~=3.6
